build/lib/build/lib/build/lib/build/lib/build/lib/build/lib/build/lib/build/lib/mzpy/__init__.py
build/lib/build/lib/build/lib/build/lib/build/lib/build/lib/build/lib/build/lib/mzpy/enrichment.py
build/lib/build/lib/build/lib/build/lib/build/lib/build/lib/build/lib/build/lib/mzpy/fragmentation.py
build/lib/build/lib/build/lib/build/lib/build/lib/build/lib/build/lib/build/lib/mzpy/metab.py
build/lib/build/lib/build/lib/build/lib/build/lib/build/lib/build/lib/build/lib/mzpy/ms.py
build/lib/build/lib/build/lib/build/lib/build/lib/build/lib/build/lib/build/lib/mzpy/mz.py
build/lib/build/lib/build/lib/build/lib/build/lib/build/lib/build/lib/build/lib/mzpy/omics.py
build/lib/build/lib/build/lib/build/lib/build/lib/build/lib/build/lib/build/lib/mzpy/peak.py
build/lib/build/lib/build/lib/build/lib/build/lib/build/lib/build/lib/build/lib/mzpy/plot.py
build/lib/build/lib/build/lib/build/lib/build/lib/build/lib/build/lib/build/lib/mzpy/precursortype.py
build/lib/build/lib/build/lib/build/lib/build/lib/build/lib/build/lib/build/lib/mzpy/rest.py
build/lib/build/lib/build/lib/build/lib/build/lib/build/lib/build/lib/build/lib/mzpy/similarity.py
build/lib/build/lib/build/lib/build/lib/build/lib/build/lib/build/lib/build/lib/mzpy/stat.py
build/lib/build/lib/build/lib/build/lib/build/lib/build/lib/build/lib/mzpy/__init__.py
build/lib/build/lib/build/lib/build/lib/build/lib/build/lib/build/lib/mzpy/enrichment.py
build/lib/build/lib/build/lib/build/lib/build/lib/build/lib/build/lib/mzpy/fragmentation.py
build/lib/build/lib/build/lib/build/lib/build/lib/build/lib/build/lib/mzpy/metab.py
build/lib/build/lib/build/lib/build/lib/build/lib/build/lib/build/lib/mzpy/ms.py
build/lib/build/lib/build/lib/build/lib/build/lib/build/lib/build/lib/mzpy/mz.py
build/lib/build/lib/build/lib/build/lib/build/lib/build/lib/build/lib/mzpy/omics.py
build/lib/build/lib/build/lib/build/lib/build/lib/build/lib/build/lib/mzpy/peak.py
mzpy-0.5.dist-info/licenses/LICENSE
mzpy-0.5.dist-info/METADATA
mzpy-0.5.dist-info/WHEEL
mzpy-0.5.dist-info/top_level.txt
mzpy-0.5.dist-info/RECORD
