Metadata-Version: 2.4
Name: mzpy
Version: 0.5
Summary: A pandas-like toolkit for MS data handling
Author-email: zq-lab <zhangq@nwsuaf.edu.cn>
Requires-Python: >=3.11
License-File: LICENSE
Requires-Dist: igraph>=0.11.4
Requires-Dist: numba>=0.57.1
Requires-Dist: numpy>=2.0
Requires-Dist: pandas>=2.2.1
Requires-Dist: plotnine>=0.14.5
Requires-Dist: pycairo>=1.28.0
Requires-Dist: rdkit>=2023.9.5
Requires-Dist: scikit-learn>=1.6.0
Requires-Dist: scipy>=1.10.0
Requires-Dist: seaborn>=0.13.2
Requires-Dist: statsmodels>=0.14.4
Requires-Dist: tqdm>=4.67.1
Dynamic: license-file
